{
     "attributes": {
          "type": "clcommon__Document_Definition__c"
     },
     "Name": "Bank Statements 6 months",
     "clcommon__Active__c": true,
     "clcommon__Child_Object_API_Name__c": null,
     "clcommon__Description__c": null,
     "clcommon__Generation_Status__c": null,
     "clcommon__Parent_Document_Definition__r": {
          "attributes": {
               "type": "clcommon__Document_Definition__c"
          },
          "genesis__External_ID__c": "Bank_Statement_Consumer"
     },
     "clcommon__Priority__c": "Normal",
     "clcommon__Release_Checksum__c": "25cdd84c6a3808abdc45a037f600803e276a1dd576e52f55917cd995bd38e96a",
     "clcommon__Required__c": true,
     "clcommon__Reuse_Document__c": false,
     "clcommon__Show_In_Portal__c": "UPLOAD_VIA_PORTAL",
     "intdm__OCR_Application_ID__c": null,
     "intdm__OCR_Application_Name__c": null,
     "intdm__OCR_Application_Token__c": null,
     "intdm__OCR_Enabled__c": false,
     "genesis__External_ID__c": "Bank_Statements_6_months_Consumer",
     "genesis__Object_Type__c": "clcommon__Party__c"
}