{
     "attributes": {
          "type": "oao__Sub_Sector__c"
     },
     "Name": "Religious, Grantmaking, Civic, Professional and Similar Organizations",
     "oao__External_Id__c": "Religious_Grantmaking_Civic_Professional_And_Similar_Organizations",
     "oao__Release_Checksum__c": "0f34e7587582de977f59cf54f5c50e4bc810f53cb27f59936cec7f812f3b2864",
     "oao__Sector__r": {
          "attributes": {
               "type": "oao__Sector__c"
          },
          "oao__External_Id__c": "Other_Services"
     }
}