{
     "attributes": {
          "type": "clcommon__Reason_Code__c"
     },
     "Name": "Poor Credit Performance with Financial Institution",
     "clcommon__Description__c": "Poor Credit Performance with Financial Institution",
     "clcommon__External_ID__c": "Poor_Credit_Performance_With_Financial_Consumer_Reason",
     "clcommon__Parent_Reason__r": {
          "attributes": {
               "type": "clcommon__Reason_Code__c"
          },
          "clcommon__External_ID__c": "Credit_Consumer_Reason"
     },
     "clcommon__Reason_Type__c": "Adverse Action",
     "clcommon__Release_Checksum__c": "b2b7b58c63960c801ea31361f2792759e6503992c50f49c18874b6d65248d566",
     "solcommon__Release_Checksum__c": null
}