{
     "attributes": {
          "type": "clcommon__Product_Purpose_Association__c"
     },
     "Name": "General Or Capital Expenditure",
     "clcommon__CL_Product__r": {
          "attributes": {
               "type": "clcommon__CL_Product__c"
          },
          "genesis__External_ID__c": "Small_Business_LOC_Secured"
     },
     "clcommon__CL_Purpose__r": {
          "attributes": {
               "type": "clcommon__CL_Purpose__c"
          },
          "clcommon__External_ID__c": "General_Or_Capital_Expenditure"
     },
     "clcommon__External_ID__c": "Small_Business_LOC_Secured_General_Or_Capital_Expenditure",
     "clcommon__Release_Checksum__c": "c0fd07b34346b69a6949d3e6c51b5094c224cf203edf6c8c4db3aed45af08e16"
}