{
     "attributes": {
          "type": "oao__Industry_Codes__c"
     },
     "Name": "Sugar Beet Farming",
     "oao__Code__c": "111991",
     "oao__Dollar_Standard__c": 2.25,
     "oao__Employee_Standard__c": null,
     "oao__External_Id__c": "111991_Sugar_Beet_Farming",
     "oao__Industry_Name__c": "Sugar Beet Farming",
     "oao__Release_Checksum__c": "9a5a9b6bd9c2264076e679ef598e9853652aa8c0ecfc6a3b11046c1dbe160567",
     "oao__Sub_Sector__r": {
          "attributes": {
               "type": "oao__Sub_Sector__c"
          },
          "oao__External_Id__c": "Crop_Production"
     }
}