{
     "attributes": {
          "type": "oao__Industry_Codes__c"
     },
     "Name": "Framing_Contractors",
     "oao__Code__c": "238130",
     "oao__Dollar_Standard__c": 16.5,
     "oao__Employee_Standard__c": null,
     "oao__External_Id__c": "238130_Framing_Contractors",
     "oao__Industry_Name__c": "Framing Contractors",
     "oao__Release_Checksum__c": "d5b79608f04876ed6d948d489120d7c4f294dc4640d8bcccb496513f1a2a612f",
     "oao__Sub_Sector__r": {
          "attributes": {
               "type": "oao__Sub_Sector__c"
          },
          "oao__External_Id__c": "Specialty_Trade_Contractors"
     }
}