{
     "attributes": {
          "type": "oao__Industry_Codes__c"
     },
     "Name": "Masonry_Contractors",
     "oao__Code__c": "238140",
     "oao__Dollar_Standard__c": 16.5,
     "oao__Employee_Standard__c": null,
     "oao__External_Id__c": "238140_Masonry_Contractors",
     "oao__Industry_Name__c": "Masonry Contractors",
     "oao__Release_Checksum__c": "ec3079206f83265bbc1f697ac8e0f3e19602461d0534bec7bcb1d1a257a67ae7",
     "oao__Sub_Sector__r": {
          "attributes": {
               "type": "oao__Sub_Sector__c"
          },
          "oao__External_Id__c": "Specialty_Trade_Contractors"
     }
}