{
     "attributes": {
          "type": "oao__Industry_Codes__c"
     },
     "Name": "Wet Corn Milling and Starch Manufacturing",
     "oao__Code__c": "311221",
     "oao__Dollar_Standard__c": null,
     "oao__Employee_Standard__c": null,
     "oao__External_Id__c": "311221_Wet_Corn_Milling_and_Starch_Manufacturing",
     "oao__Industry_Name__c": "Wet Corn Milling and Starch Manufacturing",
     "oao__Release_Checksum__c": "def1c7432561b9254d67e716d16e6cb88e81d4dc5f8bc5420fec9fc62e1a9750",
     "oao__Sub_Sector__r": {
          "attributes": {
               "type": "oao__Sub_Sector__c"
          },
          "oao__External_Id__c": "Food_Manufacturing"
     }
}