{
     "attributes": {
          "type": "oao__Industry_Codes__c"
     },
     "Name": "325413",
     "oao__Code__c": null,
     "oao__Dollar_Standard__c": null,
     "oao__Employee_Standard__c": 1250,
     "oao__External_Id__c": "325413_In_Vitro_Diagnostic_Substance_Manufacturing",
     "oao__Industry_Name__c": "In‑Vitro Diagnostic Substance Manufacturing",
     "oao__Release_Checksum__c": "cc4c0f351ff3aa11496c5e3e010f075f3b81869836070bda2aa2d40e8bd4eeb3",
     "oao__Sub_Sector__r": {
          "attributes": {
               "type": "oao__Sub_Sector__c"
          },
          "oao__External_Id__c": "Chemical_Manufacturing"
     }
}