{
     "attributes": {
          "type": "oao__Industry_Codes__c"
     },
     "Name": "Other Fabricated Wire Product Manufacturing",
     "oao__Code__c": "332618",
     "oao__Dollar_Standard__c": null,
     "oao__Employee_Standard__c": 500,
     "oao__External_Id__c": "332618_Other_Fabricated_Wire_Product_Manufacturing",
     "oao__Industry_Name__c": "Other Fabricated Wire Product Manufacturing",
     "oao__Release_Checksum__c": "f38fff10ac6add354dc6d31595a0361f3b2e3b86b2fe52ee843483b31706a8ed",
     "oao__Sub_Sector__r": {
          "attributes": {
               "type": "oao__Sub_Sector__c"
          },
          "oao__External_Id__c": "Fabricated_Metal_Product_Manufacturing"
     }
}