{
     "attributes": {
          "type": "baopoc__Industry_Codes__c"
     },
     "Name": "Relay_and_Industrial_Control_Manufacturing",
     "baopoc__Code__c": "335314",
     "baopoc__Dollar_Standard__c": null,
     "baopoc__Employee_Standard__c": 750,
     "baopoc__External_Id__c": "335314_Relay_and_Industrial_Control_Manufacturing",
     "baopoc__Industry_Name__c": "Relay and Industrial Control Manufacturing",
     "baopoc__Release_Checksum__c": "b62b05b9c5d269ada66c3d25002e409d78a1b57269e27e02f11beb094ee81f81",
     "baopoc__Sub_Sector__r": {
          "attributes": {
               "type": "baopoc__Sub_Sector__c"
          },
          "baopoc__External_Id__c": "Electrical_Equipment_Appliance_and_Component_Manufacturing"
     }
}