{
     "attributes": {
          "type": "baopoc__Industry_Codes__c"
     },
     "Name": "Aircraft_Manufacturing",
     "baopoc__Code__c": "336411",
     "baopoc__Dollar_Standard__c": null,
     "baopoc__Employee_Standard__c": 1500,
     "baopoc__External_Id__c": "336411_Aircraft_Manufacturing",
     "baopoc__Industry_Name__c": "Aircraft Manufacturing",
     "baopoc__Release_Checksum__c": "6da1ee69d7272a6923d67f030abc4b1ad45a99f657a43c51351de10fb2f85cbf",
     "baopoc__Sub_Sector__r": {
          "attributes": {
               "type": "baopoc__Sub_Sector__c"
          },
          "baopoc__External_Id__c": "Transportation_Equipment_Manufacturing6"
     }
}