{
     "attributes": {
          "type": "oao__Industry_Codes__c"
     },
     "Name": "Other Construction Material Merchant Wholesalers",
     "oao__Code__c": "423390",
     "oao__Dollar_Standard__c": null,
     "oao__Employee_Standard__c": 100,
     "oao__External_Id__c": "423390_Other_Construction_Material_Merchant_Wholesalers",
     "oao__Industry_Name__c": "Other Construction Material Merchant Wholesalers",
     "oao__Release_Checksum__c": "fd01bbcb83779cdafb298868734578cafaeb9f7166270ce03f2ff4fd1ec3fda3",
     "oao__Sub_Sector__r": {
          "attributes": {
               "type": "oao__Sub_Sector__c"
          },
          "oao__External_Id__c": "Merchant_Wholesalers_Durable_Goods"
     }
}