{
     "attributes": {
          "type": "oao__Industry_Codes__c"
     },
     "Name": "Coal_and_Other_Mineral_and_Ore_Merchant_Wholesalers",
     "oao__Code__c": "423520",
     "oao__Dollar_Standard__c": null,
     "oao__Employee_Standard__c": 100,
     "oao__External_Id__c": "423520_Coal_and_Other_Mineral_and_Ore_Merchant_Wholesalers",
     "oao__Industry_Name__c": "Coal and Other Mineral and Ore Merchant Wholesalers",
     "oao__Release_Checksum__c": "44fa61c6c06aa477b327211d6b78558a2fdcffff858bee5e3e8a0540160b7e9a",
     "oao__Sub_Sector__r": {
          "attributes": {
               "type": "oao__Sub_Sector__c"
          },
          "oao__External_Id__c": "Merchant_Wholesalers_Durable_Goods"
     }
}