{
     "attributes": {
          "type": "oao__Industry_Codes__c"
     },
     "Name": "Household Appliances, Electric Housewares, and Consumer Electronics Merchant Who",
     "oao__Code__c": "423620",
     "oao__Dollar_Standard__c": null,
     "oao__Employee_Standard__c": 200,
     "oao__External_Id__c": "423620_Household_Appliances_Electric_Housewares_And_Consumer_Electronics_Merchant_Wholesalers",
     "oao__Industry_Name__c": "Household Appliances, Electric Housewares, and Consumer Electronics Merchant Wholesalers",
     "oao__Release_Checksum__c": "9ab1778caab7852572515921fe80490bf89fe8fe6de562b81d4faa3f1accc9f0",
     "oao__Sub_Sector__r": {
          "attributes": {
               "type": "oao__Sub_Sector__c"
          },
          "oao__External_Id__c": "Merchant_Wholesalers_Durable_Goods"
     }
}