{
     "attributes": {
          "type": "baopoc__Industry_Codes__c"
     },
     "Name": "Paint_Varnish_and_Supplies_Merchant_Wholesalers",
     "baopoc__Code__c": "424950",
     "baopoc__Dollar_Standard__c": null,
     "baopoc__Employee_Standard__c": 150,
     "baopoc__External_Id__c": "424950_Paint_Varnish_and_Supplies_Merchant_Wholesalers",
     "baopoc__Industry_Name__c": "Paint, Varnish, and Supplies Merchant Wholesalers",
     "baopoc__Release_Checksum__c": "5c1e81ce87584fe23389e02751d00842bd191d8b72dfa267d3862c454284475f",
     "baopoc__Sub_Sector__r": {
          "attributes": {
               "type": "baopoc__Sub_Sector__c"
          },
          "baopoc__External_Id__c": "Merchant_Wholesalers_Nondurable_Goods"
     }
}