{
     "attributes": {
          "type": "baopoc__Industry_Codes__c"
     },
     "Name": "Scenic_and_Sightseeing_Transportation_Other",
     "baopoc__Code__c": "487990",
     "baopoc__Dollar_Standard__c": 22,
     "baopoc__Employee_Standard__c": null,
     "baopoc__External_Id__c": "487990_Scenic_and_Sightseeing_Transportation_Other",
     "baopoc__Industry_Name__c": "Scenic and Sightseeing Transportation, Other",
     "baopoc__Release_Checksum__c": "ab6374db06a46687a86073fb6c41a1ba47a96b69f31db6a597c6b1a74ec9b3f7",
     "baopoc__Sub_Sector__r": {
          "attributes": {
               "type": "baopoc__Sub_Sector__c"
          },
          "baopoc__External_Id__c": "Scenic_and_Sightseeing_Transportation"
     }
}