{
     "attributes": {
          "type": "oao__Industry_Codes__c"
     },
     "Name": "Trust, Fiduciary and Custody Activities",
     "oao__Code__c": "523991",
     "oao__Dollar_Standard__c": 41.5,
     "oao__Employee_Standard__c": null,
     "oao__External_Id__c": "523991_Trust_Fiduciary_And_Custody_Activities",
     "oao__Industry_Name__c": "Trust, Fiduciary and Custody Activities",
     "oao__Release_Checksum__c": "de5a9972554dcd90795c86b1977e695b4c5dd184a4c5231b2f3afc677e13a00f",
     "oao__Sub_Sector__r": {
          "attributes": {
               "type": "oao__Sub_Sector__c"
          },
          "oao__External_Id__c": "Financial_Investments_And_Related_Activities"
     }
}