{
     "attributes": {
          "type": "oao__Industry_Codes__c"
     },
     "Name": "Offices of Physicians, Mental Health Specialists",
     "oao__Code__c": "621112",
     "oao__Dollar_Standard__c": null,
     "oao__Employee_Standard__c": null,
     "oao__External_Id__c": "621112_Offices_of_Physicians_Mental_Health_Specialists",
     "oao__Industry_Name__c": "Offices of Physicians, Mental Health Specialists",
     "oao__Release_Checksum__c": "ad4747796bfcebce548a69b741aa4f36f5ff24f5781555cf9a0329cfe2657844",
     "oao__Sub_Sector__r": {
          "attributes": {
               "type": "oao__Sub_Sector__c"
          },
          "oao__External_Id__c": "Ambulatory_Health_Care_Services"
     }
}