{
     "attributes": {
          "type": "oao__Industry_Codes__c"
     },
     "Name": "Other Personal and Household Goods Repair and Maintenance",
     "oao__Code__c": "811490",
     "oao__Dollar_Standard__c": 8,
     "oao__Employee_Standard__c": null,
     "oao__External_Id__c": "811490_Other_Personal_and_Household_Goods_Repair_and_Maintenance",
     "oao__Industry_Name__c": "Other Personal and Household Goods Repair and Maintenance",
     "oao__Release_Checksum__c": "cedd2a5dca88ac34ede8cc44906653eacb4e7703ef3e5d947136ba8efb8cb791",
     "oao__Sub_Sector__r": {
          "attributes": {
               "type": "oao__Sub_Sector__c"
          },
          "oao__External_Id__c": "Repair_and_Maintenance"
     }
}