{
     "attributes": {
          "type": "oao__Industry_Codes__c"
     },
     "Name": "All Other Travel Arrangement and Reservation Services",
     "oao__Code__c": "561599",
     "oao__Dollar_Standard__c": null,
     "oao__Employee_Standard__c": null,
     "oao__External_Id__c": "All_Other_Travel_Arrangement_and_Reservation_Services",
     "oao__Industry_Name__c": "All Other Travel Arrangement and Reservation Services",
     "oao__Release_Checksum__c": "386ab0a5a3ebeb2cbc6ceda85df0cecc320399d85a1cb6873e2604117b786182",
     "oao__Sub_Sector__r": {
          "attributes": {
               "type": "oao__Sub_Sector__c"
          },
          "oao__External_Id__c": "Administrative_and_Support_Services"
     }
}