{
     "attributes": {
          "type": "oao__Industry_Codes__c"
     },
     "Name": "Other Services Related to Advertising",
     "oao__Code__c": "541890",
     "oao__Dollar_Standard__c": null,
     "oao__Employee_Standard__c": null,
     "oao__External_Id__c": "Other_Services_Related_to_Advertising",
     "oao__Industry_Name__c": "Other Services Related to Advertising",
     "oao__Release_Checksum__c": "4dbfdd443a479c49ead27307c39ac379a9e5cfdfd4732adb6cc76d976071e998",
     "oao__Sub_Sector__r": {
          "attributes": {
               "type": "oao__Sub_Sector__c"
          },
          "oao__External_Id__c": "Professional_Scientific_and_Technical_Services"
     }
}