{
     "attributes": {
          "type": "oao__Industry_Codes__c"
     },
     "Name": "Other Measuring and Controlling Device Manufacturing",
     "oao__Code__c": "334519",
     "oao__Dollar_Standard__c": null,
     "oao__Employee_Standard__c": null,
     "oao__External_Id__c": "Other_Measuring_and_Controlling_Device_Manufacturing",
     "oao__Industry_Name__c": "Other Measuring and Controlling Device Manufacturing",
     "oao__Release_Checksum__c": "767635514548353c532950722425b908defe85700286c00d8718f2dc84e95ba3",
     "oao__Sub_Sector__r": {
          "attributes": {
               "type": "oao__Sub_Sector__c"
          },
          "oao__External_Id__c": "Computer_and_Electronic_Product_Manufacturing"
     }
}