{
     "attributes": {
          "type": "clcommon__NavigationStructure__c"
     },
     "Name": "portal_editor_layout",
     "clcommon__Allow_Guest_User_Access__c": false,
     "clcommon__Description__c": null,
     "clcommon__Is_Editor_JSON__c": true,
     "clcommon__Is_Template__c": false,
     "clcommon__Related_Configuration_Mapping__c": null,
     "clcommon__Skip_Record_Access_For_Internal_Users__c": false,
     "clcommon__Unique_Name__c": "portal_editor_layout",
     "clcommon__data__c": {
          "start": "LayoutPage",
          "stages": {
               "LayoutPage": {
                    "layout": {
                         "name": "layoutContainer",
                         "children": [
                              {
                                   "name": "TopButtonPanel"
                              },
                              {
                                   "name": "CurrentLayout"
                              },
                              {
                                   "name": "LayoutCardView"
                              },
                              {
                                   "name": "LayoutCardViewMobile"
                              },
                              {
                                   "name": "PreviewContainer",
                                   "children": [
                                        {
                                             "name": "LayoutPreview"
                                        },
                                        {
                                             "name": "CurrentLayoutPreview"
                                        }
                                   ]
                              },
                              {
                                   "name": "LayoutDetailContainer",
                                   "children": [
                                        {
                                             "name": "LayoutDetailView"
                                        },
                                        {
                                             "name": "CurrentLayoutDetailView"
                                        },
                                        {
                                             "name": "ColorPalettePopupForLayout"
                                        },
                                        {
                                             "name": "BackgroundImagePopup"
                                        }
                                   ]
                              },
                              {
                                   "name": "BottomButtonPanel"
                              }
                         ]
                    }
               },
               "SavePage": {
                    "layout": {
                         "name": "SaveLayoutPanel"
                    }
               }
          },
          "actors": {
               "TopButtonPanel": {
                    "category": "component",
                    "type": "base-panel",
                    "appearance": {
                         "title": "Configure Layout",
                         "expansionTop": "normal"
                    },
                    "componentActions": [
                         {
                              "name": "apply",
                              "actionType": "normal",
                              "appearance": {
                                   "label": "Apply",
                                   "style": "primary",
                                   "position": "top-right"
                              },
                              "handler": {
                                   "navigation": "portal_editor_layout",
                                   "executions": [
                                        {
                                             "name": "$applyLayout;",
                                             "value": [
                                                  "portal_editor_layout",
                                                  "CurrentLayoutDetailView",
                                                  "LayoutDetailView"
                                             ]
                                        }
                                   ]
                              }
                         },
                         {
                              "name": "cancel",
                              "actionType": "normal",
                              "appearance": {
                                   "label": "Cancel",
                                   "style": "secondary",
                                   "position": "top-right"
                              },
                              "handler": {
                                   "navigation": "portal_editor_layout",
                                   "executions": [
                                        {
                                             "name": "$resetDialogJson;",
                                             "value": []
                                        }
                                   ]
                              }
                         }
                    ]
               },
               "BottomButtonPanel": {
                    "category": "component",
                    "type": "base-panel",
                    "appearance": {
                         "expansionBottom": "normal",
                         "render": "$state(LayoutDetailView).attr(Title__c); != null and $state(LayoutDetailView).attr(Title__c); != undefined"
                    },
                    "componentActions": [
                         {
                              "name": "resetLayoutChanges",
                              "actionType": "normal",
                              "appearance": {
                                   "label": "Reset Changes",
                                   "style": "normal",
                                   "position": "bottom-left",
                                   "render": "$state(LayoutDetailView).attr(Title__c); != null and $state(LayoutDetailView).attr(Title__c); != undefined and $state(CurrentLayout).attr(layoutTitle); == $state(LayoutDetailView).attr(Title__c); and $state(CurrentLayoutDetailView).attr(showReset); == true"
                              },
                              "handler": {
                                   "navigation": "portal_editor_layout",
                                   "executions": [
                                        {
                                             "name": "$resetLayoutChanges;",
                                             "value": []
                                        }
                                   ]
                              }
                         },
                         {
                              "name": "applyLayoutChange",
                              "actionType": "normal",
                              "appearance": {
                                   "label": "Preview Changes",
                                   "style": "normal"
                              },
                              "handler": {
                                   "navigation": "portal_editor_layout",
                                   "executions": [
                                        {
                                             "name": "$previewLayoutChanges;",
                                             "value": []
                                        }
                                   ]
                              }
                         },
                         {
                              "name": "saveLayout",
                              "actionType": "normal",
                              "appearance": {
                                   "label": "Create New Layout",
                                   "style": "normal"
                              },
                              "handler": {
                                   "navigation": "portal_editor_layout",
                                   "executions": [
                                        {
                                             "name": "$saveLayout;",
                                             "value": []
                                        }
                                   ],
                                   "next": "SavePage"
                              }
                         }
                    ]
               },
               "CurrentLayout": {
                    "category": "component",
                    "type": "data-model",
                    "property": {
                         "structureName": "portal_editor_current_layout",
                         "dataObject": "$editModeLayout;"
                    },
                    "appearance": {
                         "transient": true
                    }
               },
               "LayoutCardView": {
                    "category": "component",
                    "type": "card-view",
                    "property": {
                         "structureName": "portal_editor_layout_templates"
                    },
                    "appearance": {
                         "columns": 3,
                         "highlight": true,
                         "autoHighlight": {
                              "Title__c": "$state(CurrentLayout).attr(layoutTitle);"
                         },
                         "minimalDisplay": true,
                         "render": "$state(StageBarData).attr(viewportMode); == false",
                         "renderFields": {
                              "Name": "false",
                              "Default_Layout__c": "false"
                         },
                         "noLabelFields": [
                              "SVG_Thumbnail__c",
                              "Title__c"
                         ],
                         "groupBy": {
                              "field": "Default_Layout__c",
                              "titles": [
                                   {
                                        "title": "<div>Default Layouts</div>",
                                        "render": "$this.attr(Default_Layout__c); == true"
                                   },
                                   {
                                        "title": "<div>Custom Layouts</div>",
                                        "render": "$this.attr(Default_Layout__c); == false"
                                   }
                              ],
                              "ascending": true
                         },
                         "blankMessage": "<div>There is no built-in layout template to start with.<div>"
                    },
                    "generalHandlers": {
                         "clickRecord": {
                              "navigation": "portal_editor_layout",
                              "assignments": [
                                   {
                                        "field": "$nav(LayoutDetailView).property(whereClause.portalLayoutId);",
                                        "value": "$args[0].attr(id);"
                                   },
                                   {
                                        "field": "$nav(LayoutPreview).property(whereClause.portalLayoutId);",
                                        "value": "$args[0].attr(id);"
                                   }
                              ]
                         }
                    },
                    "messages": {
                         "showLoadingAnimation": true
                    }
               },
               "LayoutCardViewMobile": {
                    "category": "component",
                    "type": "card-view",
                    "property": {
                         "structureName": "portal_editor_layout_templates_mobile"
                    },
                    "appearance": {
                         "columns": 3,
                         "highlight": true,
                         "autoHighlight": {
                              "Title__c": "$state(CurrentLayout).attr(layoutTitle);"
                         },
                         "minimalDisplay": true,
                         "render": "$state(StageBarData).attr(viewportMode); == true",
                         "renderFields": {
                              "Name": "false",
                              "Default_Layout__c": "false"
                         },
                         "noLabelFields": [
                              "SVG_Thumbnail__c",
                              "Title__c"
                         ],
                         "groupBy": {
                              "field": "Default_Layout__c",
                              "titles": [
                                   {
                                        "title": "<div>Default Layouts</div>",
                                        "render": "$this.attr(Default_Layout__c); == true"
                                   },
                                   {
                                        "title": "<div>Custom Layouts</div>",
                                        "render": "$this.attr(Default_Layout__c); == false"
                                   }
                              ],
                              "ascending": true
                         },
                         "blankMessage": "<div>There is no built-in layout template to start with.<div>"
                    },
                    "generalHandlers": {
                         "clickRecord": {
                              "navigation": "portal_editor_layout",
                              "assignments": [
                                   {
                                        "field": "$nav(LayoutDetailView).property(whereClause.portalLayoutId);",
                                        "value": "$args[0].attr(id);"
                                   },
                                   {
                                        "field": "$nav(LayoutPreview).property(whereClause.portalLayoutId);",
                                        "value": "$args[0].attr(id);"
                                   }
                              ]
                         }
                    },
                    "messages": {
                         "showLoadingAnimation": true
                    }
               },
               "CurrentLayoutPreview": {
                    "category": "component",
                    "type": "detail-view",
                    "property": {
                         "structureName": "portal_editor_layout_dynamic_svg",
                         "dataObject": "$editModeLayoutDynamicSvg;"
                    },
                    "appearance": {
                         "transient": true,
                         "noLabelFields": [
                              "SVG_Full__c"
                         ],
                         "render": "$state(LayoutDetailView).attr(Title__c); != null and $state(LayoutDetailView).attr(Title__c); != undefined and $state(CurrentLayout).attr(layoutTitle); == $state(LayoutDetailView).attr(Title__c);"
                    }
               },
               "CurrentLayoutDetailView": {
                    "category": "component",
                    "type": "detail-view",
                    "property": {
                         "structureName": "portal_editor_layout_variables",
                         "dataObject": "$editModeLayoutVariables;"
                    },
                    "appearance": {
                         "editable": true,
                         "transient": true,
                         "render": "$state(LayoutDetailView).attr(Title__c); != null and $state(LayoutDetailView).attr(Title__c); != undefined and $state(CurrentLayout).attr(layoutTitle); == $state(LayoutDetailView).attr(Title__c);",
                         "fieldColumns": 3,
                         "sectionStyle": "layout",
                         "fieldStyle": {
                              "type": "side-by-side",
                              "labelWidth": "50%",
                              "valueWidth": "50%"
                         },
                         "showSectionTitle": true,
                         "renderSections": {
                              "reset": "false",
                              "svgNames": "false",
                              "gutters": "$state(LayoutDetailView).attr(Name); == \"ClsAppLayoutOne\" or $state(LayoutDetailView).attr(Name); == \"ClsPhoneLayoutOne\"",
                              "background": "$state(LayoutDetailView).attr(Name); == \"ClsAppLayoutOne\" or $state(LayoutDetailView).attr(Name); == \"ClsPhoneLayoutOne\"",
                              "horizontal": "$state(LayoutDetailView).attr(Name); != \"ClsPhoneLayoutOne\""
                         },
                         "renderFields": {
                              "primaryWidth": "$state(LayoutDetailView).attr(Name); == \"ClsLayoutThree\" or $state(LayoutDetailView).attr(Name); == \"ClsLayoutFour\" or $state(LayoutDetailView).attr(Name); == \"ClsLayoutFive\"",
                              "navigationHeight": "$state(LayoutDetailView).attr(Name); == \"ClsLayoutOne\" or $state(LayoutDetailView).attr(Name); == \"ClsLayoutTwo\" or $state(LayoutDetailView).attr(Name); == \"ClsLayoutThree\" or $state(LayoutDetailView).attr(Name); == \"ClsAppLayoutOne\" or $state(LayoutDetailView).attr(Name); == \"ClsPhoneLayoutOne\"",
                              "navigationWidth": "$state(LayoutDetailView).attr(Name); == \"ClsLayoutFour\" or $state(LayoutDetailView).attr(Name); == \"ClsLayoutFive\"",
                              "sidebar1Width": "$state(LayoutDetailView).attr(Name); == \"ClsLayoutOne\" or $state(LayoutDetailView).attr(Name); == \"ClsLayoutTwo\" or $state(LayoutDetailView).attr(Name); == \"ClsLayoutThree\" or $state(LayoutDetailView).attr(Name); == \"ClsAppLayoutOne\"",
                              "sidebar1Height": "$state(LayoutDetailView).attr(Name); == \"ClsLayoutFour\" or $state(LayoutDetailView).attr(Name); == \"ClsLayoutFive\"",
                              "showAdvertisement": "$state(LayoutDetailView).attr(Name); == \"ClsLayoutOne\" or $state(LayoutDetailView).attr(Name); == \"ClsLayoutTwo\" or $state(LayoutDetailView).attr(Name); == \"ClsLayoutFour\" or $state(LayoutDetailView).attr(Name); == \"ClsLayoutFive\"",
                              "advertisementBackgroundColor": "$state(LayoutDetailView).attr(Name); == \"ClsLayoutOne\" or $state(LayoutDetailView).attr(Name); == \"ClsLayoutTwo\" or $state(LayoutDetailView).attr(Name); == \"ClsLayoutFour\" or $state(LayoutDetailView).attr(Name); == \"ClsLayoutFive\"",
                              "advertisementTextColor": "$state(LayoutDetailView).attr(Name); == \"ClsLayoutOne\" or $state(LayoutDetailView).attr(Name); == \"ClsLayoutTwo\" or $state(LayoutDetailView).attr(Name); == \"ClsLayoutFour\" or $state(LayoutDetailView).attr(Name); == \"ClsLayoutFive\"",
                              "advertisementHeight": "$state(LayoutDetailView).attr(Name); == \"ClsLayoutOne\" or $state(LayoutDetailView).attr(Name); == \"ClsLayoutTwo\" or $state(LayoutDetailView).attr(Name); == \"ClsLayoutFour\" or $state(LayoutDetailView).attr(Name); == \"ClsLayoutFive\"",
                              "showFooter": "$state(LayoutDetailView).attr(Name); != \"ClsAppLayoutOne\" and $state(LayoutDetailView).attr(Name); != \"ClsPhoneLayoutOne\"",
                              "footerBackgroundColor": "$state(LayoutDetailView).attr(Name); != \"ClsAppLayoutOne\" and $state(LayoutDetailView).attr(Name); != \"ClsPhoneLayoutOne\"",
                              "footerTextColor": "$state(LayoutDetailView).attr(Name); != \"ClsAppLayoutOne\" and $state(LayoutDetailView).attr(Name); != \"ClsPhoneLayoutOne\"",
                              "showPrimary": "$state(LayoutDetailView).attr(Name); != \"ClsAppLayoutOne\" and $state(LayoutDetailView).attr(Name); != \"ClsPhoneLayoutOne\"",
                              "primaryBackgroundColor": "$state(LayoutDetailView).attr(Name); != \"ClsAppLayoutOne\" and $state(LayoutDetailView).attr(Name); != \"ClsPhoneLayoutOne\"",
                              "primaryTextColor": "$state(LayoutDetailView).attr(Name); != \"ClsAppLayoutOne\" and $state(LayoutDetailView).attr(Name); != \"ClsPhoneLayoutOne\"",
                              "showSecondary": "$state(LayoutDetailView).attr(Name); != \"ClsAppLayoutOne\" and $state(LayoutDetailView).attr(Name); != \"ClsPhoneLayoutOne\"",
                              "secondaryBackgroundColor": "$state(LayoutDetailView).attr(Name); != \"ClsAppLayoutOne\" and $state(LayoutDetailView).attr(Name); != \"ClsPhoneLayoutOne\"",
                              "secondaryTextColor": "$state(LayoutDetailView).attr(Name); != \"ClsAppLayoutOne\" and $state(LayoutDetailView).attr(Name); != \"ClsPhoneLayoutOne\"",
                              "showContent": "$state(LayoutDetailView).attr(Name); == \"ClsAppLayoutOne\" or $state(LayoutDetailView).attr(Name); == \"ClsPhoneLayoutOne\"",
                              "contentBackgroundColor": "$state(LayoutDetailView).attr(Name); == \"ClsAppLayoutOne\" or $state(LayoutDetailView).attr(Name); == \"ClsPhoneLayoutOne\"",
                              "contentTextColor": "$state(LayoutDetailView).attr(Name); == \"ClsAppLayoutOne\" or $state(LayoutDetailView).attr(Name); == \"ClsPhoneLayoutOne\"",
                              "showSidebar1": "$state(LayoutDetailView).attr(Name); != \"ClsPhoneLayoutOne\"",
                              "sidebar1BackgroundColor": "$state(LayoutDetailView).attr(Name); != \"ClsPhoneLayoutOne\"",
                              "sidebar1TextColor": "$state(LayoutDetailView).attr(Name); != \"ClsPhoneLayoutOne\"",
                              "showSidebar2": "$state(LayoutDetailView).attr(Name); != \"ClsPhoneLayoutOne\"",
                              "sidebar2BackgroundColor": "$state(LayoutDetailView).attr(Name); != \"ClsPhoneLayoutOne\"",
                              "sidebar2TextColor": "$state(LayoutDetailView).attr(Name); != \"ClsPhoneLayoutOne\"",
                              "backgroundTypeApp": "$this.attr(backgroundImageName); != \"\" and $state(LayoutDetailView).attr(Name); == \"ClsAppLayoutOne\"",
                              "backgroundTypePhone": "$this.attr(backgroundImageName); != \"\" and $state(LayoutDetailView).attr(Name); == \"ClsPhoneLayoutOne\"",
                              "backgroundRepeat": "$this.attr(backgroundImageName); != \"\"",
                              "backgroundImage": "$this.attr(backgroundImageName); != \"\"",
                              "backgroundImageName": false
                         },
                         "editableFields": {
                              "navigationBackgroundColor": "$this.attr(showNavigation);",
                              "navigationTextColor": "$this.attr(showNavigation);",
                              "sidebar1BackgroundColor": "$this.attr(showSidebar1);",
                              "sidebar1TextColor": "$this.attr(showSidebar1);",
                              "sidebar2BackgroundColor": "$this.attr(showSidebar2);",
                              "sidebar2TextColor": "$this.attr(showSidebar2);",
                              "advertisementBackgroundColor": "$this.attr(showAdvertisement);",
                              "advertisementTextColor": "$this.attr(showAdvertisement);",
                              "navigationHeight": "$this.attr(showNavigation);",
                              "navigationWidth": "$this.attr(showNavigation);",
                              "advertisementHeight": "$this.attr(showAdvertisement);",
                              "advertisementWidth": "$this.attr(showAdvertisement);",
                              "sidebar1Height": "$this.attr(showSidebar1);",
                              "sidebar1Width": "$this.attr(showSidebar1);",
                              "sidebar2Height": "$this.attr(showSidebar2);",
                              "sidebar2Width": "$this.attr(showSidebar2);",
                              "backgroundImage": false
                         },
                         "noLabelFields": [
                              "backgroundImage"
                         ]
                    },
                    "recordActions": [
                         {
                              "name": "chooseImage",
                              "actionType": "normal",
                              "appearance": {
                                   "label": "<span class=\"fa fa-search\"></span> Choose Image",
                                   "render": "$state(LayoutDetailView).attr(Name); == \"ClsAppLayoutOne\" or $state(LayoutDetailView).attr(Name); == \"ClsPhoneLayoutOne\"",
                                   "position": "bottom-left"
                              },
                              "handler": {
                                   "navigation": "portal_editor_layout",
                                   "executions": [
                                        {
                                             "name": "$openPopup;",
                                             "value": [
                                                  "BackgroundImagePopup",
                                                  "CurrentLayoutDetailView",
                                                  [
                                                       "backgroundImageName"
                                                  ]
                                             ]
                                        }
                                   ]
                              }
                         },
                         {
                              "name": "clearImage",
                              "actionType": "normal",
                              "appearance": {
                                   "label": "<span class=\"fa fa-times\"></span> Clear Image",
                                   "render": "$state(LayoutDetailView).attr(Name); == \"ClsAppLayoutOne\" or $state(LayoutDetailView).attr(Name); == \"ClsPhoneLayoutOne\"",
                                   "enable": "$this.attr(backgroundImageName); != \"\"",
                                   "position": "bottom-left"
                              },
                              "handler": {
                                   "navigation": "portal_editor_layout",
                                   "executions": [
                                        {
                                             "name": "$clearLayoutBackgroundImage;",
                                             "value": [
                                                  "CurrentLayoutDetailView",
                                                  "backgroundImageName"
                                             ]
                                        }
                                   ]
                              }
                         }
                    ]
               },
               "LayoutPreview": {
                    "category": "component",
                    "type": "detail-view",
                    "property": {
                         "structureName": "portal_editor_layout_preview"
                    },
                    "appearance": {
                         "render": "$state(LayoutDetailView).attr(Title__c); != null and $state(LayoutDetailView).attr(Title__c); != undefined and $state(CurrentLayout).attr(layoutTitle); != $state(LayoutDetailView).attr(Title__c);",
                         "noLabelFields": [
                              "SVG_Full__c"
                         ]
                    },
                    "messages": {
                         "hideLoadingError": true
                    }
               },
               "LayoutDetailView": {
                    "category": "component",
                    "type": "detail-view",
                    "property": {
                         "structureName": "portal_editor_layout_detail"
                    },
                    "appearance": {
                         "editable": true,
                         "fieldColumns": 3,
                         "render": "$this.attr(Title__c); != null and $this.attr(Title__c); != undefined and $state(CurrentLayout).attr(layoutTitle); != $this.attr(Title__c);",
                         "renderSections": {
                              "content": "false",
                              "svgNames": "false",
                              "gutters": "$state(LayoutDetailView).attr(Name); == \"ClsAppLayoutOne\" or $state(LayoutDetailView).attr(Name); == \"ClsPhoneLayoutOne\"",
                              "background": "$state(LayoutDetailView).attr(Name); == \"ClsAppLayoutOne\" or $state(LayoutDetailView).attr(Name); == \"ClsPhoneLayoutOne\"",
                              "horizontal": "$state(LayoutDetailView).attr(Name); != \"ClsPhoneLayoutOne\""
                         },
                         "renderFields": {
                              "Variables__c.primaryWidth": "$state(LayoutDetailView).attr(Name); == \"ClsLayoutThree\" or $state(LayoutDetailView).attr(Name); == \"ClsLayoutFour\" or $state(LayoutDetailView).attr(Name); == \"ClsLayoutFive\"",
                              "Variables__c.navigationHeight": "$state(LayoutDetailView).attr(Name); == \"ClsLayoutOne\" or $state(LayoutDetailView).attr(Name); == \"ClsLayoutTwo\" or $state(LayoutDetailView).attr(Name); == \"ClsLayoutThree\" or $state(LayoutDetailView).attr(Name); == \"ClsAppLayoutOne\"  or $state(LayoutDetailView).attr(Name); == \"ClsPhoneLayoutOne\"",
                              "Variables__c.navigationWidth": "$state(LayoutDetailView).attr(Name); == \"ClsLayoutFour\" or $state(LayoutDetailView).attr(Name); == \"ClsLayoutFive\"",
                              "Variables__c.sidebar1Width": "$state(LayoutDetailView).attr(Name); == \"ClsLayoutOne\" or $state(LayoutDetailView).attr(Name); == \"ClsLayoutTwo\" or $state(LayoutDetailView).attr(Name); == \"ClsLayoutThree\" or $state(LayoutDetailView).attr(Name); == \"ClsAppLayoutOne\"",
                              "Variables__c.sidebar1Height": "$state(LayoutDetailView).attr(Name); == \"ClsLayoutFour\" or $state(LayoutDetailView).attr(Name); == \"ClsLayoutFive\"",
                              "Variables__c.showAdvertisement": "$state(LayoutDetailView).attr(Name); == \"ClsLayoutOne\" or $state(LayoutDetailView).attr(Name); == \"ClsLayoutTwo\" or $state(LayoutDetailView).attr(Name); == \"ClsLayoutFour\" or $state(LayoutDetailView).attr(Name); == \"ClsLayoutFive\"",
                              "Variables__c.advertisementBackgroundColor": "$state(LayoutDetailView).attr(Name); == \"ClsLayoutOne\" or $state(LayoutDetailView).attr(Name); == \"ClsLayoutTwo\" or $state(LayoutDetailView).attr(Name); == \"ClsLayoutFour\" or $state(LayoutDetailView).attr(Name); == \"ClsLayoutFive\"",
                              "Variables__c.advertisementTextColor": "$state(LayoutDetailView).attr(Name); == \"ClsLayoutOne\" or $state(LayoutDetailView).attr(Name); == \"ClsLayoutTwo\" or $state(LayoutDetailView).attr(Name); == \"ClsLayoutFour\" or $state(LayoutDetailView).attr(Name); == \"ClsLayoutFive\"",
                              "Variables__c.advertisementHeight": "$state(LayoutDetailView).attr(Name); == \"ClsLayoutOne\" or $state(LayoutDetailView).attr(Name); == \"ClsLayoutTwo\" or $state(LayoutDetailView).attr(Name); == \"ClsLayoutFour\" or $state(LayoutDetailView).attr(Name); == \"ClsLayoutFive\"",
                              "Variables__c.showFooter": "$state(LayoutDetailView).attr(Name); != \"ClsAppLayoutOne\" and $state(LayoutDetailView).attr(Name); != \"ClsPhoneLayoutOne\"",
                              "Variables__c.footerBackgroundColor": "$state(LayoutDetailView).attr(Name); != \"ClsAppLayoutOne\" and $state(LayoutDetailView).attr(Name); != \"ClsPhoneLayoutOne\"",
                              "Variables__c.footerTextColor": "$state(LayoutDetailView).attr(Name); != \"ClsAppLayoutOne\" and $state(LayoutDetailView).attr(Name); != \"ClsPhoneLayoutOne\"",
                              "Variables__c.showPrimary": "$state(LayoutDetailView).attr(Name); != \"ClsAppLayoutOne\" and $state(LayoutDetailView).attr(Name); != \"ClsPhoneLayoutOne\"",
                              "Variables__c.primaryBackgroundColor": "$state(LayoutDetailView).attr(Name); != \"ClsAppLayoutOne\" and $state(LayoutDetailView).attr(Name); != \"ClsPhoneLayoutOne\"",
                              "Variables__c.primaryTextColor": "$state(LayoutDetailView).attr(Name); != \"ClsAppLayoutOne\" and $state(LayoutDetailView).attr(Name); != \"ClsPhoneLayoutOne\"",
                              "Variables__c.showSecondary": "$state(LayoutDetailView).attr(Name); != \"ClsAppLayoutOne\" and $state(LayoutDetailView).attr(Name); != \"ClsPhoneLayoutOne\"",
                              "Variables__c.secondaryBackgroundColor": "$state(LayoutDetailView).attr(Name); != \"ClsAppLayoutOne\" and $state(LayoutDetailView).attr(Name); != \"ClsPhoneLayoutOne\"",
                              "Variables__c.secondaryTextColor": "$state(LayoutDetailView).attr(Name); != \"ClsAppLayoutOne\" and $state(LayoutDetailView).attr(Name); != \"ClsPhoneLayoutOne\"",
                              "Variables__c.showContent": "$state(LayoutDetailView).attr(Name); == \"ClsAppLayoutOne\" or $state(LayoutDetailView).attr(Name); == \"ClsPhoneLayoutOne\"",
                              "Variables__c.contentBackgroundColor": "$state(LayoutDetailView).attr(Name); == \"ClsAppLayoutOne\" or $state(LayoutDetailView).attr(Name); == \"ClsPhoneLayoutOne\"",
                              "Variables__c.contentTextColor": "$state(LayoutDetailView).attr(Name); == \"ClsAppLayoutOne\" or $state(LayoutDetailView).attr(Name); == \"ClsPhoneLayoutOne\"",
                              "Variables__c.showSidebar1": "$state(LayoutDetailView).attr(Name); != \"ClsPhoneLayoutOne\"",
                              "Variables__c.sidebar1BackgroundColor": "$state(LayoutDetailView).attr(Name); != \"ClsPhoneLayoutOne\"",
                              "Variables__c.sidebar1TextColor": "$state(LayoutDetailView).attr(Name); != \"ClsPhoneLayoutOne\"",
                              "Variables__c.showSidebar2": "$state(LayoutDetailView).attr(Name); != \"ClsPhoneLayoutOne\"",
                              "Variables__c.sidebar2BackgroundColor": "$state(LayoutDetailView).attr(Name); != \"ClsPhoneLayoutOne\"",
                              "Variables__c.sidebar2TextColor": "$state(LayoutDetailView).attr(Name); != \"ClsPhoneLayoutOne\"",
                              "Variables__c.backgroundTypeApp": "$this.attr(Variables__c.backgroundImageName); != \"\" and $state(LayoutDetailView).attr(Name); == \"ClsAppLayoutOne\"",
                              "Variables__c.backgroundTypePhone": "$this.attr(Variables__c.backgroundImageName); != \"\" and $state(LayoutDetailView).attr(Name); == \"ClsPhoneLayoutOne\"",
                              "Variables__c.backgroundRepeat": "$this.attr(Variables__c.backgroundImageName); != \"\"",
                              "Variables__c.backgroundImage": "$this.attr(Variables__c.backgroundImageName); != \"\"",
                              "Variables__c.backgroundImageName": false
                         },
                         "editableFields": {
                              "Variables__c.navigationBackgroundColor": "$this.attr(Variables__c.showNavigation);",
                              "Variables__c.navigationTextColor": "$this.attr(Variables__c.showNavigation);",
                              "Variables__c.sidebar1BackgroundColor": "$this.attr(Variables__c.showSidebar1);",
                              "Variables__c.sidebar1TextColor": "$this.attr(Variables__c.showSidebar1);",
                              "Variables__c.sidebar2BackgroundColor": "$this.attr(Variables__c.showSidebar2);",
                              "Variables__c.sidebar2TextColor": "$this.attr(Variables__c.showSidebar2);",
                              "Variables__c.advertisementBackgroundColor": "$this.attr(Variables__c.showAdvertisement);",
                              "Variables__c.advertisementTextColor": "$this.attr(Variables__c.showAdvertisement);",
                              "Variables__c.navigationHeight": "$this.attr(Variables__c.showNavigation);",
                              "Variables__c.navigationWidth": "$this.attr(Variables__c.showNavigation);",
                              "Variables__c.advertisementHeight": "$this.attr(Variables__c.showAdvertisement);",
                              "Variables__c.advertisementWidth": "$this.attr(Variables__c.showAdvertisement);",
                              "Variables__c.sidebar1Height": "$this.attr(Variables__c.showSidebar1);",
                              "Variables__c.sidebar1Width": "$this.attr(Variables__c.showSidebar1);",
                              "Variables__c.sidebar2Height": "$this.attr(Variables__c.showSidebar2);",
                              "Variables__c.sidebar2Width": "$this.attr(Variables__c.showSidebar2);",
                              "Variables__c.backgroundImage": false
                         },
                         "noLabelFields": [
                              "Variables__c.backgroundImage"
                         ],
                         "sectionStyle": "layout",
                         "fieldStyle": {
                              "type": "side-by-side",
                              "labelWidth": "50%",
                              "valueWidth": "50%"
                         },
                         "showSectionTitle": true,
                         "appendedStructure": {
                              "sections": [
                                   {
                                        "id": "f3b4",
                                        "name": "general",
                                        "title": "General",
                                        "fields": [
                                             {
                                                  "id": "7bb5",
                                                  "fieldName": "Variables__c.backgroundColor",
                                                  "fieldUi": {
                                                       "fieldType": "colorpicker",
                                                       "label": "Background Color",
                                                       "pickerOptions": {
                                                            "popupName": "ColorPalettePopupForLayout",
                                                            "allowTransparent": true
                                                       }
                                                  }
                                             },
                                             {
                                                  "id": "cc31",
                                                  "fieldName": "Variables__c.textColor",
                                                  "fieldUi": {
                                                       "fieldType": "colorpicker",
                                                       "label": "Text Color",
                                                       "pickerOptions": {
                                                            "popupName": "ColorPalettePopupForLayout"
                                                       }
                                                  }
                                             },
                                             {
                                                  "id": "6f4f",
                                                  "fieldName": "Variables__c.appMaxWidth",
                                                  "fieldUi": {
                                                       "fieldType": "string",
                                                       "label": "Max Width"
                                                  }
                                             }
                                        ]
                                   },
                                   {
                                        "id": "8438",
                                        "name": "colors",
                                        "title": "Visibility and Colors",
                                        "fields": [
                                             {
                                                  "id": "eb75",
                                                  "fieldName": "Variables__c.showHeader",
                                                  "fieldUi": {
                                                       "fieldType": "boolean",
                                                       "label": "Header",
                                                       "placeholderText": "Display"
                                                  }
                                             },
                                             {
                                                  "id": "c879",
                                                  "fieldName": "Variables__c.headerBackgroundColor",
                                                  "fieldUi": {
                                                       "fieldType": "colorpicker",
                                                       "label": "Background Color",
                                                       "pickerOptions": {
                                                            "popupName": "ColorPalettePopupForLayout",
                                                            "allowTransparent": true
                                                       }
                                                  }
                                             },
                                             {
                                                  "id": "5d6f",
                                                  "fieldName": "Variables__c.headerTextColor",
                                                  "fieldUi": {
                                                       "fieldType": "colorpicker",
                                                       "label": "Text Color",
                                                       "pickerOptions": {
                                                            "popupName": "ColorPalettePopupForLayout"
                                                       }
                                                  }
                                             },
                                             {
                                                  "id": "dd6f",
                                                  "fieldName": "Variables__c.showContent",
                                                  "fieldUi": {
                                                       "fieldType": "boolean",
                                                       "label": "Content",
                                                       "placeholderText": "Display"
                                                  }
                                             },
                                             {
                                                  "id": "f0d7",
                                                  "fieldName": "Variables__c.contentBackgroundColor",
                                                  "fieldUi": {
                                                       "fieldType": "colorpicker",
                                                       "label": "Background Color",
                                                       "pickerOptions": {
                                                            "popupName": "ColorPalettePopupForLayout",
                                                            "allowTransparent": true
                                                       }
                                                  }
                                             },
                                             {
                                                  "id": "9d6d",
                                                  "fieldName": "Variables__c.contentTextColor",
                                                  "fieldUi": {
                                                       "fieldType": "colorpicker",
                                                       "label": "Text Color",
                                                       "pickerOptions": {
                                                            "popupName": "ColorPalettePopupForLayout"
                                                       }
                                                  }
                                             },
                                             {
                                                  "id": "7971",
                                                  "fieldName": "Variables__c.showPrimary",
                                                  "fieldUi": {
                                                       "fieldType": "boolean",
                                                       "label": "Primary Content",
                                                       "placeholderText": "Display"
                                                  }
                                             },
                                             {
                                                  "id": "4cd0",
                                                  "fieldName": "Variables__c.primaryBackgroundColor",
                                                  "fieldUi": {
                                                       "fieldType": "colorpicker",
                                                       "label": "Background Color",
                                                       "pickerOptions": {
                                                            "popupName": "ColorPalettePopupForLayout",
                                                            "allowTransparent": true
                                                       }
                                                  }
                                             },
                                             {
                                                  "id": "3c62",
                                                  "fieldName": "Variables__c.primaryTextColor",
                                                  "fieldUi": {
                                                       "fieldType": "colorpicker",
                                                       "label": "Text Color",
                                                       "pickerOptions": {
                                                            "popupName": "ColorPalettePopupForLayout"
                                                       }
                                                  }
                                             },
                                             {
                                                  "id": "0c50",
                                                  "fieldName": "Variables__c.showSecondary",
                                                  "fieldUi": {
                                                       "fieldType": "boolean",
                                                       "label": "Secondary Content",
                                                       "placeholderText": "Display"
                                                  }
                                             },
                                             {
                                                  "id": "e815",
                                                  "fieldName": "Variables__c.secondaryBackgroundColor",
                                                  "fieldUi": {
                                                       "fieldType": "colorpicker",
                                                       "label": "Background Color",
                                                       "pickerOptions": {
                                                            "popupName": "ColorPalettePopupForLayout",
                                                            "allowTransparent": true
                                                       }
                                                  }
                                             },
                                             {
                                                  "id": "2537",
                                                  "fieldName": "Variables__c.secondaryTextColor",
                                                  "fieldUi": {
                                                       "fieldType": "colorpicker",
                                                       "label": "Text Color",
                                                       "pickerOptions": {
                                                            "popupName": "ColorPalettePopupForLayout"
                                                       }
                                                  }
                                             },
                                             {
                                                  "id": "1603",
                                                  "fieldName": "Variables__c.showFooter",
                                                  "fieldUi": {
                                                       "fieldType": "boolean",
                                                       "label": "Footer",
                                                       "placeholderText": "Display"
                                                  }
                                             },
                                             {
                                                  "id": "c423",
                                                  "fieldName": "Variables__c.footerBackgroundColor",
                                                  "fieldUi": {
                                                       "fieldType": "colorpicker",
                                                       "label": "Background Color",
                                                       "pickerOptions": {
                                                            "popupName": "ColorPalettePopupForLayout",
                                                            "allowTransparent": true
                                                       }
                                                  }
                                             },
                                             {
                                                  "id": "76e0",
                                                  "fieldName": "Variables__c.footerTextColor",
                                                  "fieldUi": {
                                                       "fieldType": "colorpicker",
                                                       "label": "Text Color",
                                                       "pickerOptions": {
                                                            "popupName": "ColorPalettePopupForLayout"
                                                       }
                                                  }
                                             },
                                             {
                                                  "id": "9861",
                                                  "fieldName": "Variables__c.showNavigation",
                                                  "fieldUi": {
                                                       "fieldType": "boolean",
                                                       "label": "Navigation",
                                                       "placeholderText": "Display"
                                                  }
                                             },
                                             {
                                                  "id": "ab8f",
                                                  "fieldName": "Variables__c.navigationBackgroundColor",
                                                  "fieldUi": {
                                                       "fieldType": "colorpicker",
                                                       "label": "Background Color",
                                                       "pickerOptions": {
                                                            "popupName": "ColorPalettePopupForLayout",
                                                            "allowTransparent": true
                                                       }
                                                  }
                                             },
                                             {
                                                  "id": "937d",
                                                  "fieldName": "Variables__c.navigationTextColor",
                                                  "fieldUi": {
                                                       "fieldType": "colorpicker",
                                                       "label": "Text Color",
                                                       "pickerOptions": {
                                                            "popupName": "ColorPalettePopupForLayout"
                                                       }
                                                  }
                                             },
                                             {
                                                  "id": "0001",
                                                  "fieldName": "Variables__c.showSidebar1",
                                                  "fieldUi": {
                                                       "fieldType": "boolean",
                                                       "label": "Sidebar 1",
                                                       "placeholderText": "Display"
                                                  }
                                             },
                                             {
                                                  "id": "d1a3",
                                                  "fieldName": "Variables__c.sidebar1BackgroundColor",
                                                  "fieldUi": {
                                                       "fieldType": "colorpicker",
                                                       "label": "Background Color",
                                                       "pickerOptions": {
                                                            "popupName": "ColorPalettePopupForLayout",
                                                            "allowTransparent": true
                                                       }
                                                  }
                                             },
                                             {
                                                  "id": "b136",
                                                  "fieldName": "Variables__c.sidebar1TextColor",
                                                  "fieldUi": {
                                                       "fieldType": "colorpicker",
                                                       "label": "Text Color",
                                                       "pickerOptions": {
                                                            "popupName": "ColorPalettePopupForLayout"
                                                       }
                                                  }
                                             },
                                             {
                                                  "id": "7710",
                                                  "fieldName": "Variables__c.showSidebar2",
                                                  "fieldUi": {
                                                       "fieldType": "boolean",
                                                       "label": "Sidebar 2",
                                                       "placeholderText": "Display"
                                                  }
                                             },
                                             {
                                                  "id": "c5f1",
                                                  "fieldName": "Variables__c.sidebar2BackgroundColor",
                                                  "fieldUi": {
                                                       "fieldType": "colorpicker",
                                                       "label": "Background Color",
                                                       "pickerOptions": {
                                                            "popupName": "ColorPalettePopupForLayout",
                                                            "allowTransparent": true
                                                       }
                                                  }
                                             },
                                             {
                                                  "id": "aba9",
                                                  "fieldName": "Variables__c.sidebar2TextColor",
                                                  "fieldUi": {
                                                       "fieldType": "colorpicker",
                                                       "label": "Text Color",
                                                       "pickerOptions": {
                                                            "popupName": "ColorPalettePopupForLayout"
                                                       }
                                                  }
                                             },
                                             {
                                                  "id": "f8d4",
                                                  "fieldName": "Variables__c.showAdvertisement",
                                                  "fieldUi": {
                                                       "fieldType": "boolean",
                                                       "label": "Advertisement",
                                                       "placeholderText": "Display"
                                                  }
                                             },
                                             {
                                                  "id": "ae45",
                                                  "fieldName": "Variables__c.advertisementBackgroundColor",
                                                  "fieldUi": {
                                                       "fieldType": "colorpicker",
                                                       "label": "Background Color",
                                                       "pickerOptions": {
                                                            "popupName": "ColorPalettePopupForLayout",
                                                            "allowTransparent": true
                                                       }
                                                  }
                                             },
                                             {
                                                  "id": "0a7e",
                                                  "fieldName": "Variables__c.advertisementTextColor",
                                                  "fieldUi": {
                                                       "fieldType": "colorpicker",
                                                       "label": "Text Color",
                                                       "pickerOptions": {
                                                            "popupName": "ColorPalettePopupForLayout"
                                                       }
                                                  }
                                             }
                                        ]
                                   },
                                   {
                                        "id": "ca1e",
                                        "name": "vertical",
                                        "title": "Vertical Heights",
                                        "fields": [
                                             {
                                                  "id": "2c62",
                                                  "fieldName": "Variables__c.headerHeight",
                                                  "fieldUi": {
                                                       "fieldType": "string",
                                                       "label": "Header"
                                                  }
                                             },
                                             {
                                                  "id": "4be7",
                                                  "fieldName": "Variables__c.navigationHeight",
                                                  "fieldUi": {
                                                       "fieldType": "string",
                                                       "label": "Navigation"
                                                  }
                                             },
                                             {
                                                  "id": "85ea",
                                                  "fieldName": "Variables__c.advertisementHeight",
                                                  "fieldUi": {
                                                       "fieldType": "string",
                                                       "label": "Advertisement"
                                                  }
                                             },
                                             {
                                                  "id": "9145",
                                                  "fieldName": "Variables__c.sidebar1Height",
                                                  "fieldUi": {
                                                       "fieldType": "string",
                                                       "label": "Sidebar 1"
                                                  }
                                             }
                                        ]
                                   },
                                   {
                                        "id": "86bf",
                                        "name": "horizontal",
                                        "title": "Horizontal Widths",
                                        "fields": [
                                             {
                                                  "id": "ad85",
                                                  "fieldName": "Variables__c.navigationWidth",
                                                  "fieldUi": {
                                                       "fieldType": "string",
                                                       "label": "Navigation"
                                                  }
                                             },
                                             {
                                                  "id": "712c",
                                                  "fieldName": "Variables__c.sidebar1Width",
                                                  "fieldUi": {
                                                       "fieldType": "string",
                                                       "label": "Sidebar 1"
                                                  }
                                             },
                                             {
                                                  "id": "1a57",
                                                  "fieldName": "Variables__c.sidebar2Width",
                                                  "fieldUi": {
                                                       "fieldType": "string",
                                                       "label": "Sidebar 2"
                                                  }
                                             },
                                             {
                                                  "id": "2da9",
                                                  "fieldName": "Variables__c.primaryWidth",
                                                  "fieldUi": {
                                                       "fieldType": "string",
                                                       "label": "Primary Content"
                                                  }
                                             }
                                        ]
                                   },
                                   {
                                        "id": "7408",
                                        "name": "gutters",
                                        "title": "Global Gutters",
                                        "fields": [
                                             {
                                                  "id": "9245",
                                                  "fieldName": "Variables__c.gutterWidth",
                                                  "fieldUi": {
                                                       "fieldType": "number",
                                                       "label": "Width",
                                                       "required": true,
                                                       "regex": "^\\d+([.]\\d+)?$",
                                                       "format": {
                                                            "suffix": "px"
                                                       },
                                                       "messages": {
                                                            "requiredErrorText": "<span class='fa fa-exclamation'></span> Cannot be blank",
                                                            "regexErrorText": "<span class='fa fa-exclamation'></span> Has to be a positive number or 0"
                                                       }
                                                  }
                                             },
                                             {
                                                  "id": "5c79",
                                                  "fieldName": "Variables__c.gutterHeight",
                                                  "fieldUi": {
                                                       "fieldType": "number",
                                                       "label": "Height",
                                                       "required": true,
                                                       "regex": "^\\d+([.]\\d+)?$",
                                                       "format": {
                                                            "suffix": "px"
                                                       },
                                                       "messages": {
                                                            "requiredErrorText": "<span class='fa fa-exclamation'></span> Cannot be blank",
                                                            "regexErrorText": "<span class='fa fa-exclamation'></span> Has to be a positive number or 0"
                                                       }
                                                  }
                                             }
                                        ]
                                   },
                                   {
                                        "id": "19b7",
                                        "name": "background",
                                        "title": "Background Image",
                                        "fields": [
                                             {
                                                  "id": "0ff2",
                                                  "fieldName": "Variables__c.backgroundImageName",
                                                  "fieldUi": {
                                                       "fieldType": "string",
                                                       "label": "Name"
                                                  }
                                             },
                                             {
                                                  "id": "0cc6",
                                                  "fieldName": "Variables__c.backgroundImage",
                                                  "fieldUi": {
                                                       "fieldType": "image",
                                                       "linkTemplate": "/resource/$global.attr(staticResourceTimestamp);/$this.attr(Variables__c.backgroundImageName);",
                                                       "imageAltText": "$this.attr(Variables__c.backgroundImageName);"
                                                  }
                                             },
                                             {
                                                  "id": "d279",
                                                  "fieldName": "Variables__c.backgroundTypeApp",
                                                  "fieldUi": {
                                                       "fieldType": "radiobuttons",
                                                       "label": "Background Size",
                                                       "required": true,
                                                       "selectOptions": [
                                                            {
                                                                 "optionText": "Content Only",
                                                                 "optionValue": "Content"
                                                            },
                                                            {
                                                                 "optionText": "Below Header and Navigation",
                                                                 "optionValue": "Main"
                                                            },
                                                            {
                                                                 "optionText": "Entire Application",
                                                                 "optionValue": "App"
                                                            }
                                                       ]
                                                  }
                                             },
                                             {
                                                  "id": "7cef",
                                                  "fieldName": "Variables__c.backgroundTypePhone",
                                                  "fieldUi": {
                                                       "fieldType": "radiobuttons",
                                                       "label": "Background Size",
                                                       "required": true,
                                                       "selectOptions": [
                                                            {
                                                                 "optionText": "Content Only",
                                                                 "optionValue": "Content"
                                                            },
                                                            {
                                                                 "optionText": "Entire Application",
                                                                 "optionValue": "App"
                                                            }
                                                       ]
                                                  }
                                             },
                                             {
                                                  "id": "8521",
                                                  "fieldName": "Variables__c.backgroundRepeat",
                                                  "fieldUi": {
                                                       "fieldType": "radiobuttons",
                                                       "label": "Background Style",
                                                       "required": true,
                                                       "selectOptions": [
                                                            {
                                                                 "optionText": "Repeat",
                                                                 "optionValue": "repeat"
                                                            },
                                                            {
                                                                 "optionText": "Stretch",
                                                                 "optionValue": "no-repeat"
                                                            }
                                                       ]
                                                  }
                                             }
                                        ]
                                   },
                                   {
                                        "id": "2330",
                                        "name": "svgNames",
                                        "fields": [
                                             {
                                                  "id": "f5a8",
                                                  "fieldName": "Variables__c.headerText",
                                                  "fieldUi": {
                                                       "fieldType": "string",
                                                       "label": "",
                                                       "defaultValue": "Header"
                                                  }
                                             },
                                             {
                                                  "id": "20b5",
                                                  "fieldName": "Variables__c.footerText",
                                                  "fieldUi": {
                                                       "fieldType": "string",
                                                       "label": "",
                                                       "defaultValue": "Footer"
                                                  }
                                             },
                                             {
                                                  "id": "b2e2",
                                                  "fieldName": "Variables__c.navigationText",
                                                  "fieldUi": {
                                                       "fieldType": "string",
                                                       "label": "",
                                                       "defaultValue": "Navigation"
                                                  }
                                             },
                                             {
                                                  "id": "c181",
                                                  "fieldName": "Variables__c.advertisementText",
                                                  "fieldUi": {
                                                       "fieldType": "string",
                                                       "label": "",
                                                       "defaultValue": "Advertisement"
                                                  }
                                             },
                                             {
                                                  "id": "9220",
                                                  "fieldName": "Variables__c.sidebar1Text",
                                                  "fieldUi": {
                                                       "fieldType": "string",
                                                       "label": "",
                                                       "defaultValue": "Sidebar 1"
                                                  }
                                             },
                                             {
                                                  "id": "c4fb",
                                                  "fieldName": "Variables__c.sidebar2Text",
                                                  "fieldUi": {
                                                       "fieldType": "string",
                                                       "label": "",
                                                       "defaultValue": "Sidebar 2"
                                                  }
                                             },
                                             {
                                                  "id": "d79d",
                                                  "fieldName": "Variables__c.primaryText",
                                                  "fieldUi": {
                                                       "fieldType": "string",
                                                       "label": "",
                                                       "defaultValue": "Primary Content"
                                                  }
                                             },
                                             {
                                                  "id": "ac27",
                                                  "fieldName": "Variables__c.secondaryText",
                                                  "fieldUi": {
                                                       "fieldType": "string",
                                                       "label": "",
                                                       "defaultValue": "Secondary Content"
                                                  }
                                             },
                                             {
                                                  "id": "ad2f",
                                                  "fieldName": "Variables__c.contentText",
                                                  "fieldUi": {
                                                       "fieldType": "string",
                                                       "label": "",
                                                       "defaultValue": "Content"
                                                  }
                                             }
                                        ]
                                   }
                              ]
                         }
                    },
                    "recordActions": [
                         {
                              "name": "chooseImage",
                              "actionType": "normal",
                              "appearance": {
                                   "label": "<span class=\"fa fa-search\"></span> Choose Image",
                                   "render": "$state(LayoutDetailView).attr(Name); == \"ClsAppLayoutOne\" or $state(LayoutDetailView).attr(Name); == \"ClsPhoneLayoutOne\"",
                                   "position": "bottom-left"
                              },
                              "handler": {
                                   "navigation": "portal_editor_layout",
                                   "executions": [
                                        {
                                             "name": "$openPopup;",
                                             "value": [
                                                  "BackgroundImagePopup",
                                                  "LayoutDetailView",
                                                  [
                                                       "Variables__c.backgroundImageName"
                                                  ]
                                             ]
                                        }
                                   ]
                              }
                         },
                         {
                              "name": "clearImage",
                              "actionType": "normal",
                              "appearance": {
                                   "label": "<span class=\"fa fa-times\"></span> Clear Image",
                                   "render": "$state(LayoutDetailView).attr(Name); == \"ClsAppLayoutOne\" or $state(LayoutDetailView).attr(Name); == \"ClsPhoneLayoutOne\"",
                                   "enable": "$this.attr(Variables__c.backgroundImageName); != \"\"",
                                   "position": "bottom-left"
                              },
                              "handler": {
                                   "navigation": "portal_editor_layout",
                                   "executions": [
                                        {
                                             "name": "$clearLayoutBackgroundImage;",
                                             "value": [
                                                  "LayoutDetailView",
                                                  "Variables__c.backgroundImageName"
                                             ]
                                        }
                                   ]
                              }
                         }
                    ],
                    "messages": {
                         "hideLoadingError": true,
                         "showLoadingAnimation": true
                    }
               },
               "ColorPalettePopupForLayout": {
                    "mode": "popup",
                    "category": "component",
                    "type": "base-panel",
                    "property": {
                         "structureName": "portal_editor_branding_color_palette_popup",
                         "dataObject": "$editModeBrandingColorPalette;"
                    },
                    "appearance": {
                         "editable": true,
                         "transient": true,
                         "noLabelFields": [
                              "currentColor"
                         ],
                         "popup": {
                              "direction": "bottom",
                              "anchor": "cursor",
                              "width": 234,
                              "height": 308,
                              "margin": 20,
                              "borderColor": "#767676",
                              "backgroundColor": "#ffffff"
                         }
                    },
                    "generalHandlers": {
                         "fieldChange": {
                              "currentColor": {
                                   "navigation": "portal_editor_layout",
                                   "executions": [
                                        {
                                             "name": "$updateBrandingColor;",
                                             "value": [
                                                  "ColorPalettePopupForLayout"
                                             ]
                                        }
                                   ]
                              }
                         }
                    }
               },
               "BackgroundImagePopup": {
                    "mode": "popup",
                    "category": "component",
                    "type": "queue-view",
                    "property": {
                         "structureName": "portal_editor_branding_image_queue_view"
                    },
                    "appearance": {
                         "expansionBottom": "normal",
                         "fieldColumns": 2,
                         "noLabelFields": [
                              "Id"
                         ],
                         "spanFields": [
                              "Id",
                              "Name"
                         ],
                         "sortableFields": [
                              "Name",
                              "LastModifiedDate"
                         ],
                         "sortedField": {
                              "name": "LastModifiedDate",
                              "ascending": false
                         },
                         "sortText": {
                              "sortBy": "Sort By",
                              "aToZ": "(A to Z)",
                              "zToA": "(Z to A)",
                              "mostRecentFirst": "(Most Recent First)",
                              "mostRecentLast": "(Most Recent Last)"
                         },
                         "popup": {
                              "direction": "left",
                              "anchor": "bottom",
                              "width": 380,
                              "height": 600,
                              "margin": 30,
                              "borderColor": "#767676",
                              "backgroundColor": "#ffffff",
                              "overflowY": "auto"
                         }
                    },
                    "componentActions": [
                         {
                              "name": "upload",
                              "actionType": "upload",
                              "property": {
                                   "uploadType": "static-resource"
                              },
                              "appearance": {
                                   "label": "Upload",
                                   "style": "primary",
                                   "position": "bottom-right"
                              },
                              "successHandler": {
                                   "navigation": "portal_editor_layout",
                                   "executions": [
                                        {
                                             "name": "$updateStaticResourceTimestamp;",
                                             "value": []
                                        }
                                   ],
                                   "updates": [
                                        {
                                             "name": "$nav.reloads.add;",
                                             "value": "BackgroundImagePopup"
                                        }
                                   ]
                              }
                         }
                    ],
                    "recordActions": [
                         {
                              "name": "replace",
                              "actionType": "upload",
                              "property": {
                                   "uploadType": "static-resource",
                                   "staticResourceName": "$this.attr(Name);"
                              },
                              "appearance": {
                                   "label": "<span class='fa fa-pencil'></span>",
                                   "position": "top-right"
                              },
                              "successHandler": {
                                   "navigation": "portal_editor_layout",
                                   "executions": [
                                        {
                                             "name": "$updateStaticResourceTimestamp;",
                                             "value": []
                                        }
                                   ],
                                   "updates": [
                                        {
                                             "name": "$nav.reloads.add;",
                                             "value": "BackgroundImagePopup"
                                        }
                                   ]
                              }
                         }
                    ],
                    "generalHandlers": {
                         "clickRecord": {
                              "navigation": "portal_editor_layout",
                              "executions": [
                                   {
                                        "name": "$applyPopup;",
                                        "value": [
                                             "BackgroundImagePopup",
                                             [
                                                  "Name"
                                             ]
                                        ]
                                   },
                                   {
                                        "name": "$resetPopupLocation;",
                                        "value": [
                                             "BackgroundImagePopup"
                                        ]
                                   }
                              ]
                         }
                    }
               },
               "SaveLayoutPanel": {
                    "category": "component",
                    "type": "base-panel",
                    "property": {
                         "structureName": "portal_editor_layout_save_panel"
                    },
                    "appearance": {
                         "editable": true,
                         "transient": true,
                         "renderSections": {
                              "content": "false"
                         },
                         "expansionBottom": "normal"
                    },
                    "componentActions": [
                         {
                              "name": "cancel",
                              "actionType": "normal",
                              "appearance": {
                                   "label": "Cancel",
                                   "style": "secondary",
                                   "position": "bottom-left"
                              },
                              "handler": {
                                   "navigation": "portal_editor_layout",
                                   "next": "LayoutPage"
                              }
                         },
                         {
                              "name": "save",
                              "actionType": "save",
                              "appearance": {
                                   "label": "Save",
                                   "style": "primary",
                                   "position": "bottom-right"
                              },
                              "successHandler": {
                                   "navigation": "portal_editor_layout",
                                   "assignments": [
                                        {
                                             "field": "$nav(LayoutCardView).appearance(autoHighlight);",
                                             "value": {
                                                  "Title__c": "$result.attr(Title__c);"
                                             }
                                        },
                                        {
                                             "field": "$nav(LayoutCardViewMobile).appearance(autoHighlight);",
                                             "value": {
                                                  "Title__c": "$result.attr(Title__c);"
                                             }
                                        }
                                   ],
                                   "updates": [
                                        {
                                             "name": "$nav.reloads.add;",
                                             "value": [
                                                  "LayoutCardView",
                                                  "LayoutCardViewMobile"
                                             ]
                                        }
                                   ],
                                   "next": "LayoutPage"
                              }
                         }
                    ]
               }
          },
          "settings": {
               "locale": "en-us",
               "currency": "USD",
               "minimumFractionDigits": 2,
               "uploadText": {
                    "completed": "Completed",
                    "cancelInProgress": "Cancel",
                    "removeError": "<span class=\"fa fa-times\"></span>"
               }
          },
          "messages": {
               "loadingAnimationText": "<span><span class=\"fa fa-spinner\"></span>Loading...</span>",
               "savingAnimationText": "<span><span class=\"fa fa-spinner\"></span>Saving...</span>",
               "submitAnimationText": "<span><span class=\"fa fa-spinner\"></span>Sending...</span>",
               "loadingFailureText": "<span><span class=\"fa fa-exclamation-triangle\"></span>Fail to load</span>",
               "saveSuccessText": "<span><span class=\"fa fa-check\"></span>Succeed</span>",
               "saveFailureText": "<span><span class=\"fa fa-exclamation-triangle\"></span>Fail to save</span>",
               "submitSuccessText": "<span><span class=\"fa fa-check\"></span>Succeed</span>",
               "submitFailureText": "<span><span class=\"fa fa-exclamation-triangle\"></span>Fail to submit</span>",
               "submitExpirationText": "<span><span class=\"fa fa-exclamation-triangle\"></span>Fail to submit</span>",
               "uploadFailureText": "<span><span class=\"fa fa-exclamation-triangle\"></span>Fail to upload</span>",
               "uploadFileTooLargeError": "<span><span class=\"fa fa-exclamation-triangle\"></span>File too large</span>"
          }
     },
     "clcommon__External_ID__c": "portal_editor_layout",
     "clcommon__Release_Checksum__c": "3b60bf8b7a68a08d5e34ffc95a9ae8bc09e694049f0260b60740d3cc89ab6a6d"
}