{
     "attributes": {
          "type": "solcommon__Industry_Code__c"
     },
     "Name": "311512",
     "solcommon__Dollar_Standard__c": null,
     "solcommon__Employee_Standard__c": 750,
     "solcommon__External_Id__c": "311512_Creamery_Butter_Manufacturing",
     "solcommon__Industry_Name__c": "Creamery Butter Manufacturing",
     "solcommon__Industry_Sub_Sector__r": {
          "attributes": {
               "type": "solcommon__Industry_Sub_Sector__c"
          },
          "solcommon__External_Id__c": "Food_Manufacturing"
     },
     "solcommon__Release_Checksum__c": "021afdb1a7f0734985eaf538765551d02975e67390af0c38885e1c50cc6a558c"
}