{
     "attributes": {
          "type": "solcommon__Industry_Code__c"
     },
     "Name": "621498",
     "solcommon__Dollar_Standard__c": 22.5,
     "solcommon__Employee_Standard__c": null,
     "solcommon__External_Id__c": "621498_All_Other_Outpatient_Care_Centers",
     "solcommon__Industry_Name__c": "All Other Outpatient Care Centers",
     "solcommon__Industry_Sub_Sector__r": {
          "attributes": {
               "type": "solcommon__Industry_Sub_Sector__c"
          },
          "solcommon__External_Id__c": "Ambulatory_Health_Care_Services"
     },
     "solcommon__Release_Checksum__c": "4b48b9e57d5d4d75c96e6927f2e67e1c6c9f0936e350145f8f7631e97f92fb74"
}