{
     "attributes": {
          "type": "solcommon__Portal_Application_Status_Mapping__c"
     },
     "solcommon__Application_Status__c": "NEW - ENTERED",
     "solcommon__Asset_Class__r": {
          "attributes": {
               "type": "clcommon__Asset_Class__c"
          },
          "clcommon__External_ID__c": "Small_Business_Real_Estate"
     },
     "solcommon__Portal_Status__c": "Pending Submission",
     "solcommon__External_Id__c": "Pending_Submission_New_Entered_SBRE",
     "solcommon__Release_Checksum__c": "d4463cb50cb8fa566c758ef72a2320932179e17fc7a98b9dfb1886a2f5b5c01a"
}