{
     "attributes": {
          "type": "clcommon__Industry_Classification_Code__c"
     },
     "Name": "212391",
     "clcommon__Code__c": null,
     "clcommon__Description__c": null,
     "clcommon__External_Id__c": "212391_Potash_Soda_And_Borate_Mineral_Mining",
     "clcommon__Financial_Statement_Template__r": null,
     "clcommon__Release_Checksum__c": "69e34311077058896ee2b6d812876e388daba4c13fe815da27772fb855b0d5a8",
     "genesis__Dollar_Standard__c": null,
     "genesis__Employee_Standard__c": 750,
     "genesis__Industry_Name__c": "Potash, Soda, and Borate Mineral Mining",
     "genesis__Industry_Sub_Sector__r": {
          "attributes": {
               "type": "genesis__Industry_Sub_Sector__c"
          },
          "genesis__External_Id__c": "Mining_Except_Oil_And_Gas"
     }
}