{
     "attributes": {
          "type": "clcommon__Industry_Classification_Code__c"
     },
     "Name": "326299",
     "clcommon__Code__c": null,
     "clcommon__Description__c": null,
     "clcommon__External_Id__c": "326299_All_Other_Rubber_Product_Manufacturing",
     "clcommon__Financial_Statement_Template__r": null,
     "clcommon__Release_Checksum__c": "91326d2908283da28270901adb8053b1d54a96b700f4c33a00f65d24337b5728",
     "genesis__Dollar_Standard__c": null,
     "genesis__Employee_Standard__c": 500,
     "genesis__Industry_Name__c": "All Other Rubber Product Manufacturing",
     "genesis__Industry_Sub_Sector__r": {
          "attributes": {
               "type": "genesis__Industry_Sub_Sector__c"
          },
          "genesis__External_Id__c": "Plastics_And_Rubber_Products_Manufacturing"
     }
}