{
     "attributes": {
          "type": "clcommon__Industry_Classification_Code__c"
     },
     "Name": "331420",
     "clcommon__Code__c": null,
     "clcommon__Description__c": null,
     "clcommon__External_Id__c": "331420_Copper_Rolling_Drawing_Extruding_And_Alloying",
     "clcommon__Financial_Statement_Template__r": null,
     "clcommon__Release_Checksum__c": "e337093c1b8e99543f028b54b9ab63a36814ed122aaad32776862a1c0559a1a5",
     "genesis__Dollar_Standard__c": null,
     "genesis__Employee_Standard__c": 1000,
     "genesis__Industry_Name__c": "Copper Rolling, Drawing, Extruding, and Alloying",
     "genesis__Industry_Sub_Sector__r": {
          "attributes": {
               "type": "genesis__Industry_Sub_Sector__c"
          },
          "genesis__External_Id__c": "Primary_Metal_Manufacturing"
     }
}