{
     "attributes": {
          "type": "clcommon__Industry_Classification_Code__c"
     },
     "Name": "332216",
     "clcommon__Code__c": null,
     "clcommon__Description__c": null,
     "clcommon__External_Id__c": "332216_Saw_Blade_And_Handtool_Manufacturing",
     "clcommon__Financial_Statement_Template__r": null,
     "clcommon__Release_Checksum__c": "a81d95a9659d332022c3831d82c8b3382ee2c4f4070000388c0bd1e18f7059be",
     "genesis__Dollar_Standard__c": null,
     "genesis__Employee_Standard__c": 750,
     "genesis__Industry_Name__c": "Saw Blade and Handtool Manufacturing",
     "genesis__Industry_Sub_Sector__r": {
          "attributes": {
               "type": "genesis__Industry_Sub_Sector__c"
          },
          "genesis__External_Id__c": "Fabricated_Metal_Product_Manufacturing"
     }
}