{
     "attributes": {
          "type": "clcommon__Industry_Classification_Code__c"
     },
     "Name": "339114",
     "genesis__Dollar_Standard__c": null,
     "genesis__Employee_Standard__c": 750,
     "clcommon__External_Id__c": "339114_Dental_Equipment_And_Supplies_Manufacturing",
     "genesis__Industry_Name__c": "Dental Equipment and Supplies Manufacturing",
     "genesis__Industry_Sub_Sector__r": {
          "attributes": {
               "type": "genesis__Industry_Sub_Sector__c"
          },
          "genesis__External_Id__c": "Miscellaneous_Manufacturing"
     },
     "clcommon__Release_Checksum__c": "634d708b19155fb74f8459b33555352ce60137f960de2091e454db7dfc1028d2"
}