{
     "attributes": {
          "type": "clcommon__Industry_Classification_Code__c"
     },
     "Name": "423990",
     "clcommon__Code__c": null,
     "clcommon__Description__c": null,
     "clcommon__External_Id__c": "423990_Other_Miscellaneous_Durable_Goods_Merchant_Wholesalers",
     "clcommon__Financial_Statement_Template__r": null,
     "clcommon__Release_Checksum__c": "e1182bf6c995a22e6c094748ad1f6ec67a82decdf915c367d3a95f5872655076",
     "genesis__Dollar_Standard__c": null,
     "genesis__Employee_Standard__c": 100,
     "genesis__Industry_Name__c": "Other Miscellaneous Durable Goods Merchant Wholesalers",
     "genesis__Industry_Sub_Sector__r": {
          "attributes": {
               "type": "genesis__Industry_Sub_Sector__c"
          },
          "genesis__External_Id__c": "Merchant_Wholesalers_Durable_Goods"
     }
}