{
     "attributes": {
          "type": "clcommon__Industry_Classification_Code__c"
     },
     "Name": "532283",
     "genesis__Dollar_Standard__c": 36,
     "genesis__Employee_Standard__c": null,
     "clcommon__External_Id__c": "532283_Home_Health_Equipment_Rental",
     "genesis__Industry_Name__c": "Home Health Equipment Rental",
     "genesis__Industry_Sub_Sector__r": {
          "attributes": {
               "type": "genesis__Industry_Sub_Sector__c"
          },
          "genesis__External_Id__c": "Rental_And_Leasing_Services"
     },
     "clcommon__Release_Checksum__c": "34cef592557c928f405452d8d561fa930971322258deb08fcf006e28a3561827"
}