{
     "attributes": {
          "type": "clcommon__Industry_Classification_Code__c"
     },
     "Name": "561613",
     "clcommon__Code__c": null,
     "clcommon__Description__c": null,
     "clcommon__External_Id__c": "561613_Armored_Car_Services",
     "clcommon__Financial_Statement_Template__r": null,
     "clcommon__Release_Checksum__c": "0f9df9873817e11f944ad42e0e60d035afe5a9e56ed589dd594487fed4c26a3c",
     "genesis__Dollar_Standard__c": 38,
     "genesis__Employee_Standard__c": null,
     "genesis__Industry_Name__c": "Armored Car Services",
     "genesis__Industry_Sub_Sector__r": {
          "attributes": {
               "type": "genesis__Industry_Sub_Sector__c"
          },
          "genesis__External_Id__c": "Administrative_And_Support_Services"
     }
}