{
     "attributes": {
          "type": "clcommon__Industry_Classification_Code__c"
     },
     "Name": "713110",
     "genesis__Dollar_Standard__c": 41.5,
     "genesis__Employee_Standard__c": null,
     "clcommon__External_Id__c": "713110_Amusement_And_Theme_Parks",
     "genesis__Industry_Name__c": "Amusement and Theme Parks",
     "genesis__Industry_Sub_Sector__r": {
          "attributes": {
               "type": "genesis__Industry_Sub_Sector__c"
          },
          "genesis__External_Id__c": "Amusement_Gambling_And_Recreation_Industries"
     },
     "clcommon__Release_Checksum__c": "21e27e35198cec18335d4794a1471c42958dad0339fb860d7904c8a1d4f12363"
}