{
     "attributes": {
          "type": "clcommon__Industry_Classification_Code__c"
     },
     "Name": "713990",
     "genesis__Dollar_Standard__c": 8,
     "genesis__Employee_Standard__c": null,
     "clcommon__External_Id__c": "713990_All_Other_Amusement_And_Recreation_Industries",
     "genesis__Industry_Name__c": "All Other Amusement and Recreation Industries",
     "genesis__Industry_Sub_Sector__r": {
          "attributes": {
               "type": "genesis__Industry_Sub_Sector__c"
          },
          "genesis__External_Id__c": "Amusement_Gambling_And_Recreation_Industries"
     },
     "clcommon__Release_Checksum__c": "f411df7afcf5e75d0c31d6530407d76d652fb3323eb756464b097f51d232ceac"
}